amgi_types/__init__.py
amgi_types/py.typed
amgi_types-0.32.0.dist-info/licenses/LICENSE
amgi_types-0.32.0.dist-info/WHEEL
amgi_types-0.32.0.dist-info/METADATA
amgi_types-0.32.0.dist-info/RECORD
