Metadata-Version: 2.4
Name: amgi-types
Version: 0.32.0
Summary: AMGI Types
Author: jack.burridge
Author-email: jack.burridge <jack.burridge@mail.com>
License-Expression: MIT
License-File: LICENSE
Classifier: Development Status :: 2 - Pre-Alpha
Classifier: Framework :: AsyncIO
Classifier: Programming Language :: Python :: 3 :: Only
Classifier: Programming Language :: Python :: 3.10
Classifier: Programming Language :: Python :: 3.11
Classifier: Programming Language :: Python :: 3.12
Classifier: Programming Language :: Python :: 3.13
Classifier: Programming Language :: Python :: 3.14
Requires-Dist: typing-extensions>=4.15.0 ; python_full_version < '3.11'
Requires-Python: >=3.10
Project-URL: Changelog, https://github.com/asyncfast/amgi/blob/main/CHANGELOG.md
Project-URL: Homepage, https://github.com/asyncfast/amgi/tree/main/packages/amgi-types
Project-URL: Issues, https://github.com/asyncfast/amgi/issues/
Project-URL: Repository, https://github.com/asyncfast/amgi/
